[
  {
    "word": "(컴퓨터 시스템이나 프로그램의) 오류",
    "meaning": "bug"
  },
  {
    "word": "~과는 반대로",
    "meaning": "contrary to"
  },
  {
    "word": "엄청난, 거대한",
    "meaning": "enormous"
  },
  {
    "word": "~할 것으로 예상되다",
    "meaning": "be projected to do"
  },
  {
    "word": "노동 인구",
    "meaning": "workforce"
  },
  {
    "word": "혁신적인",
    "meaning": "innovative"
  },
  {
    "word": "한정된",
    "meaning": "finite"
  },
  {
    "word": "매장 층",
    "meaning": "deposit"
  },
  {
    "word": "주장하다",
    "meaning": "maintain"
  },
  {
    "word": "근원암",
    "meaning": "source rock"
  },
  {
    "word": "지질학자",
    "meaning": "geologist"
  },
  {
    "word": "궁극적인",
    "meaning": "ultimate"
  },
  {
    "word": "종래의, 전통적인",
    "meaning": "conventional"
  },
  {
    "word": "기체의",
    "meaning": "gaseous"
  },
  {
    "word": "지표",
    "meaning": "indicator"
  },
  {
    "word": "그사이에, 그동안에",
    "meaning": "in the meantime"
  },
  {
    "word": "혁신적인",
    "meaning": "innovative"
  },
  {
    "word": "행동의, 행동에 관한",
    "meaning": "behavioral"
  },
  {
    "word": "규모",
    "meaning": "scale"
  },
  {
    "word": "과대평가하다",
    "meaning": "overvalue"
  },
  {
    "word": "비율",
    "meaning": "factor"
  },
  {
    "word": "불일치",
    "meaning": "mismatch"
  },
  {
    "word": "이득",
    "meaning": "gain"
  },
  {
    "word": "~보다 더 크다",
    "meaning": "outweigh"
  },
  {
    "word": "잠재적인",
    "meaning": "potential"
  },
  {
    "word": "받아들이다, 채택하다",
    "meaning": "adopt"
  },
  {
    "word": "응용 프로그램",
    "meaning": "application"
  },
  {
    "word": "~이 ...하도록 강요하다",
    "meaning": "force ~ to do"
  },
  {
    "word": "(매개체로) 전달하다, 영향을 주다",
    "meaning": "mediate"
  },
  {
    "word": "비언어적인",
    "meaning": "nonverbal"
  }
]